client/__init__.py
client/client.py
client/client_database.py
client/client_transport.py
client/descs.py
client/metaclasses.py
client/common/__init__.py
client/common/decorators.py
client/common/errors.py
client/common/utils.py
client/common/variables.py
client/log/__init__.py
client/log/client_log_config.py
client/log/server_log_config.py
client/ui/__init__.py
client/ui/client_add_contact.py
client/ui/client_chat.py
client/ui/gui.py
client/ui/login.py
client/unit_tests/__init__.py
client/unit_tests/test_client.py
client/unit_tests/test_server.py
client/unit_tests/test_utils.py
gui_messenger_client-0.0.1.dist-info/METADATA
gui_messenger_client-0.0.1.dist-info/WHEEL
gui_messenger_client-0.0.1.dist-info/top_level.txt
gui_messenger_client-0.0.1.dist-info/RECORD
