Metadata-Version: 2.1
Name: gui-messenger-client
Version: 0.0.1
Summary: Gui messenger client
Home-page: UNKNOWN
Author: Demin Dmitry
Author-email: sampaccs@mail.ru
License: UNKNOWN
Platform: UNKNOWN
Requires-Dist: PyQt5
Requires-Dist: sqlalchemy
Requires-Dist: pycryptodome
Requires-Dist: pycryptodomex
